{
  "model": "banglabert",
  "seed": 42,
  "best_val_f1": 0.9223,
  "test_metrics": {
    "binary": {
      "accuracy": 0.9247,
      "macro_f1": 0.9238,
      "weighted_f1": 0.9247,
      "mcc": 0.8476
    },
    "abuse_type": {
      "accuracy": 0.0014,
      "macro_f1": 0.0054,
      "weighted_f1": 0.0001,
      "mcc": 0.0011
    }
  },
  "history": {
    "train_loss": [
      0.1164,
      0.0875,
      0.0667,
      0.0487,
      0.0353,
      0.0267,
      0.0208,
      0.0168,
      0.0136,
      0.0112
    ],
    "val_f1": [
      0.8358,
      0.8625,
      0.8792,
      0.8989,
      0.9112,
      0.9184,
      0.9218,
      0.9218,
      0.9221,
      0.9223
    ]
  }
}